nlp_templates/__init__.py
nlp_templates/py.typed
nlp_templates/base/__init__.py
nlp_templates/base/base_classifier.py
nlp_templates/classifiers/__init__.py
nlp_templates/classifiers/hierarchical_multiclass_classifier.py
nlp_templates/classifiers/hierarchical_nn_classifier.py
nlp_templates/classifiers/simple_multiclass_classifier.py
nlp_templates/classifiers/text_classifier.py
nlp_templates/evaluation/__init__.py
nlp_templates/evaluation/metrics.py
nlp_templates/evaluation/visualizations.py
nlp_templates/models/__init__.py
nlp_templates/models/neural_network.py
nlp_templates/preprocessing/__init__.py
nlp_templates/preprocessing/config_loader.py
nlp_templates/preprocessing/data_augmentor.py
nlp_templates/preprocessing/data_splitter.py
nlp_templates/preprocessing/text_preprocessor.py
nlp_templates/tuning/__init__.py
nlp_templates/tuning/optuna_tuner.py
nlp_templates/utils/__init__.py
nlp_templates/utils/db_utils.py
nlp_templates/utils/embedding_generation.py
nlp_templates/utils/logging_utils.py
nlp_templates/utils/mlflow_manager.py
nlp_templates-0.2.0.dist-info/licenses/LICENSE
nlp_templates-0.2.0.dist-info/METADATA
nlp_templates-0.2.0.dist-info/WHEEL
nlp_templates-0.2.0.dist-info/top_level.txt
nlp_templates-0.2.0.dist-info/RECORD
