Metadata-Version: 2.4
Name: nlp-templates
Version: 0.2.0
Summary: Production-ready ML classification templates with hierarchical and neural network classifiers
Author-email: Bhavinkumar Rathava <bhavinr9@gmail.com>
Maintainer-email: Bhavinkumar Rathava <bhavinr9@gmail.com>
License-Expression: MIT
Project-URL: Homepage, https://github.com/bhavinr9/nlp-templates
Project-URL: Documentation, https://github.com/bhavinr9/nlp-templates#readme
Project-URL: Repository, https://github.com/bhavinr9/nlp-templates.git
Project-URL: Issues, https://github.com/bhavinr9/nlp-templates/issues
Project-URL: Changelog, https://github.com/bhavinr9/nlp-templates/blob/main/CHANGELOG.md
Keywords: machine-learning,nlp,classification,hierarchical-classification,neural-network,deep-learning,sklearn,pytorch,mlflow
Classifier: Development Status :: 4 - Beta
Classifier: Intended Audience :: Developers
Classifier: Intended Audience :: Science/Research
Classifier: Operating System :: OS Independent
Classifier: Programming Language :: Python :: 3
Classifier: Programming Language :: Python :: 3.9
Classifier: Programming Language :: Python :: 3.10
Classifier: Programming Language :: Python :: 3.11
Classifier: Programming Language :: Python :: 3.12
Classifier: Programming Language :: Python :: 3.13
Classifier: Topic :: Scientific/Engineering :: Artificial Intelligence
Classifier: Topic :: Scientific/Engineering :: Information Analysis
Classifier: Typing :: Typed
Requires-Python: >=3.9
License-File: LICENSE
Requires-Dist: scikit-learn>=1.0.0
Requires-Dist: pandas>=1.3.0
Requires-Dist: numpy>=1.21.0
Requires-Dist: pyyaml>=6.0
Requires-Dist: matplotlib>=3.5.0
Requires-Dist: seaborn>=0.11.0
Provides-Extra: torch
Requires-Dist: torch>=2.0.0; extra == "torch"
Provides-Extra: embeddings
Requires-Dist: sentence-transformers>=2.2.0; extra == "embeddings"
Provides-Extra: mlflow
Requires-Dist: mlflow>=2.0.0; extra == "mlflow"
Provides-Extra: tuning
Requires-Dist: optuna>=3.0.0; extra == "tuning"
Provides-Extra: dev
Requires-Dist: pytest>=7.0; extra == "dev"
Requires-Dist: pytest-cov>=3.0; extra == "dev"
Requires-Dist: black>=22.0; extra == "dev"
Requires-Dist: flake8>=4.0; extra == "dev"
Requires-Dist: isort>=5.0; extra == "dev"
Requires-Dist: mypy>=1.0; extra == "dev"
Requires-Dist: pre-commit>=3.0; extra == "dev"
Provides-Extra: docs
Requires-Dist: sphinx>=4.0; extra == "docs"
Requires-Dist: sphinx-rtd-theme>=1.0; extra == "docs"
Requires-Dist: myst-parser>=0.18; extra == "docs"
Provides-Extra: all
Requires-Dist: nlp-templates[embeddings,mlflow,torch,tuning]; extra == "all"
Dynamic: license-file
